npu_compiler/__init__.py
npu_compiler/__main__.py
npu_compiler/v100/__init__.py
npu_compiler/v100/addr_manager.cpython-36m-x86_64-linux-gnu.so
npu_compiler/v100/compiler.cpython-36m-x86_64-linux-gnu.so
npu_compiler/v100/config.cpython-36m-x86_64-linux-gnu.so
npu_compiler/v100/gg_ops_manager.cpython-36m-x86_64-linux-gnu.so
npu_compiler/v100/group.cpython-36m-x86_64-linux-gnu.so
npu_compiler/v100/group_manager.cpython-36m-x86_64-linux-gnu.so
npu_compiler/v100/ops.cpython-36m-x86_64-linux-gnu.so
npu_compiler/v100/ops_connect.cpython-36m-x86_64-linux-gnu.so
npu_compiler/v100/ops_dict.cpython-36m-x86_64-linux-gnu.so
npu_compiler/v100/ops_firmware.cpython-36m-x86_64-linux-gnu.so
npu_compiler/v100/ops_functools.py
npu_compiler/v100/ops_manager.cpython-36m-x86_64-linux-gnu.so
npu_compiler/v100/ops_merge.cpython-36m-x86_64-linux-gnu.so
npu_compiler/v100/ops_optimize.cpython-36m-x86_64-linux-gnu.so
npu_compiler/v100/ops_replace.cpython-36m-x86_64-linux-gnu.so
npu_compiler/v100/ops_support.cpython-36m-x86_64-linux-gnu.so
npu_compiler/v100/pack.cpython-36m-x86_64-linux-gnu.so
npu_compiler/v100/py2c_ops.cpython-36m-x86_64-linux-gnu.so
npu_compiler/v100/session.cpython-36m-x86_64-linux-gnu.so
npu_compiler/v100/sub_info.cpython-36m-x86_64-linux-gnu.so
npu_compiler/v100/gen_cmd/fw/firmware16_0.bin
npu_compiler/v100/gen_cmd/fw/firmware16_10016.bin
npu_compiler/v100/gen_cmd/fw/firmware16_15016.bin
npu_compiler/v100/gen_cmd/fw/firmware32_0.bin
npu_compiler/v100/gen_cmd/fw/firmware32_10016.bin
npu_compiler/v100/gen_cmd/fw/firmware32_15016.bin
npu_compiler/v100/gen_cmd/output/libnpu_compiler_mpw.so
npu_compiler/v100/gen_cmd/output/libnpu_compiler_nre.so
npu_compiler/v120/__init__.py
npu_compiler/v120/addr_manager.cpython-36m-x86_64-linux-gnu.so
npu_compiler/v120/compiler.cpython-36m-x86_64-linux-gnu.so
npu_compiler/v120/config.cpython-36m-x86_64-linux-gnu.so
npu_compiler/v120/decrypt_data.cpython-36m-x86_64-linux-gnu.so
npu_compiler/v120/dep_manager.cpython-36m-x86_64-linux-gnu.so
npu_compiler-1.6.5.dist-info/METADATA
npu_compiler-1.6.5.dist-info/WHEEL
npu_compiler-1.6.5.dist-info/top_level.txt
npu_compiler-1.6.5.dist-info/RECORD
