Metadata-Version: 2.1
Name: npu-compiler
Version: 1.6.5
Summary: produce NPU instructions
Home-page: http://ai.nationalchip.com/
Author: Hangzhou Nationalchip Inc.
Author-email: zhengdi@nationalchip.com
License: MIT Licence
Keywords: npu gxdnn nationalchip
Platform: UNKNOWN
Classifier: Development Status :: 3 - Alpha
Classifier: Intended Audience :: Developers
Classifier: Topic :: Software Development :: Libraries :: Python Modules
Classifier: License :: OSI Approved :: MIT License
Classifier: Programming Language :: Python :: 3.6
Classifier: Programming Language :: Python :: 3.7
Classifier: Programming Language :: Python :: 3.8
Requires-Dist: numpy
Requires-Dist: pyyaml
Requires-Dist: wheel
Requires-Dist: six
Requires-Dist: humanize
Requires-Dist: prettytable
Requires-Dist: scipy
Requires-Dist: matplotlib
Requires-Dist: pillow
Requires-Dist: pydot (==1.4.2)
Requires-Dist: cryptography (>=3.3.2)
Requires-Dist: cffi (==1.15.1)
